[{"cars": [{"done": false, "pos": [6, 3], "dir": 0, "goal": [0, 2]}, {"done": false, "pos": [6, 2], "dir": 0, "goal": [0, 2]}], "road": [[0.0, 0.0, 1.0, 1.0, 1.0, 0.0, 0.0, 0.0], [0.0, 0.0, 1.0, 1.0, 1.0, 0.0, 0.0, 0.0], [0.0, 0.0, 1.0, 1.0, 1.0, 0.0, 0.0, 0.0], [0.0, 0.0, 1.0, 1.0, 1.0, 0.0, 0.0, 0.0], [0.0, 0.0, 1.0, 1.0, 1.0, 0.0, 0.0, 0.0], [0.0, 0.0, 1.0, 1.0, 1.0, 0.0, 0.0, 0.0], [0.0, 0.0, 1.0, 1.0, 1.0, 0.0, 0.0, 0.0], [0.0, 0.0, 1.0, 1.0, 1.0, 0.0, 0.0, 0.0]]}, [{"action": 0, "message": "center goal north"}, {"action": 1, "message": "south going north"}], {"cars": [{"done": false, "pos": [6, 3], "dir": 0, "goal": [0, 2]}, {"done": false, "pos": [5, 2], "dir": 0, "goal": [0, 2]}], "road": [[0.0, 0.0, 1.0, 1.0, 1.0, 0.0, 0.0, 0.0], [0.0, 0.0, 1.0, 1.0, 1.0, 0.0, 0.0, 0.0], [0.0, 0.0, 1.0, 1.0, 1.0, 0.0, 0.0, 0.0], [0.0, 0.0, 1.0, 1.0, 1.0, 0.0, 0.0, 0.0], [0.0, 0.0, 1.0, 1.0, 1.0, 0.0, 0.0, 0.0], [0.0, 0.0, 1.0, 1.0, 1.0, 0.0, 0.0, 0.0], [0.0, 0.0, 1.0, 1.0, 1.0, 0.0, 0.0, 0.0], [0.0, 0.0, 1.0, 1.0, 1.0, 0.0, 0.0, 0.0]]}, [{"action": 0, "message": "will wait bottom"}, {"action": 1, "message": "goal north left"}], {"cars": [{"done": false, "pos": [6, 3], "dir": 0, "goal": [0, 2]}, {"done": false, "pos": [4, 2], "dir": 0, "goal": [0, 2]}], "road": [[0.0, 0.0, 1.0, 1.0, 1.0, 0.0, 0.0, 0.0], [0.0, 0.0, 1.0, 1.0, 1.0, 0.0, 0.0, 0.0], [0.0, 0.0, 1.0, 1.0, 1.0, 0.0, 0.0, 0.0], [0.0, 0.0, 1.0, 1.0, 1.0, 0.0, 0.0, 0.0], [0.0, 0.0, 1.0, 1.0, 1.0, 0.0, 0.0, 0.0], [0.0, 0.0, 1.0, 1.0, 1.0, 0.0, 0.0, 0.0], [0.0, 0.0, 1.0, 1.0, 1.0, 0.0, 0.0, 0.0], [0.0, 0.0, 1.0, 1.0, 1.0, 0.0, 0.0, 0.0]]}, [{"action": 0, "message": "when close talk"}, {"action": 1, "message": ""}], {"cars": [{"done": false, "pos": [6, 3], "dir": 0, "goal": [0, 2]}, {"done": false, "pos": [3, 2], "dir": 0, "goal": [0, 2]}], "road": [[0.0, 0.0, 1.0, 1.0, 1.0, 0.0, 0.0, 0.0], [0.0, 0.0, 1.0, 1.0, 1.0, 0.0, 0.0, 0.0], [0.0, 0.0, 1.0, 1.0, 1.0, 0.0, 0.0, 0.0], [0.0, 0.0, 1.0, 1.0, 1.0, 0.0, 0.0, 0.0], [0.0, 0.0, 1.0, 1.0, 1.0, 0.0, 0.0, 0.0], [0.0, 0.0, 1.0, 1.0, 1.0, 0.0, 0.0, 0.0], [0.0, 0.0, 1.0, 1.0, 1.0, 0.0, 0.0, 0.0], [0.0, 0.0, 1.0, 1.0, 1.0, 0.0, 0.0, 0.0]]}, [{"action": 0, "message": "goal same here"}, {"action": 1, "message": ""}], {"cars": [{"done": false, "pos": [6, 3], "dir": 0, "goal": [0, 2]}, {"done": false, "pos": [2, 2], "dir": 0, "goal": [0, 2]}], "road": [[0.0, 0.0, 1.0, 1.0, 1.0, 0.0, 0.0, 0.0], [0.0, 0.0, 1.0, 1.0, 1.0, 0.0, 0.0, 0.0], [0.0, 0.0, 1.0, 1.0, 1.0, 0.0, 0.0, 0.0], [0.0, 0.0, 1.0, 1.0, 1.0, 0.0, 0.0, 0.0], [0.0, 0.0, 1.0, 1.0, 1.0, 0.0, 0.0, 0.0], [0.0, 0.0, 1.0, 1.0, 1.0, 0.0, 0.0, 0.0], [0.0, 0.0, 1.0, 1.0, 1.0, 0.0, 0.0, 0.0], [0.0, 0.0, 1.0, 1.0, 1.0, 0.0, 0.0, 0.0]]}, [{"action": 0, "message": ""}, {"action": 1, "message": "close"}], {"cars": [{"done": false, "pos": [6, 3], "dir": 0, "goal": [0, 2]}, {"done": false, "pos": [1, 2], "dir": 0, "goal": [0, 2]}], "road": [[0.0, 0.0, 1.0, 1.0, 1.0, 0.0, 0.0, 0.0], [0.0, 0.0, 1.0, 1.0, 1.0, 0.0, 0.0, 0.0], [0.0, 0.0, 1.0, 1.0, 1.0, 0.0, 0.0, 0.0], [0.0, 0.0, 1.0, 1.0, 1.0, 0.0, 0.0, 0.0], [0.0, 0.0, 1.0, 1.0, 1.0, 0.0, 0.0, 0.0], [0.0, 0.0, 1.0, 1.0, 1.0, 0.0, 0.0, 0.0], [0.0, 0.0, 1.0, 1.0, 1.0, 0.0, 0.0, 0.0], [0.0, 0.0, 1.0, 1.0, 1.0, 0.0, 0.0, 0.0]]}, [{"action": 2, "message": ""}, {"action": 1, "message": ""}], {"cars": [{"done": false, "pos": [6, 2], "dir": 3, "goal": [0, 2]}, {"done": true, "pos": [0, 2], "dir": 0, "goal": [0, 2]}], "road": [[0.0, 0.0, 1.0, 1.0, 1.0, 0.0, 0.0, 0.0], [0.0, 0.0, 1.0, 1.0, 1.0, 0.0, 0.0, 0.0], [0.0, 0.0, 1.0, 1.0, 1.0, 0.0, 0.0, 0.0], [0.0, 0.0, 1.0, 1.0, 1.0, 0.0, 0.0, 0.0], [0.0, 0.0, 1.0, 1.0, 1.0, 0.0, 0.0, 0.0], [0.0, 0.0, 1.0, 1.0, 1.0, 0.0, 0.0, 0.0], [0.0, 0.0, 1.0, 1.0, 1.0, 0.0, 0.0, 0.0], [0.0, 0.0, 1.0, 1.0, 1.0, 0.0, 0.0, 0.0]]}, [{"action": 3, "message": "pulling in left"}, {"action": 0, "message": ""}], {"cars": [{"done": false, "pos": [5, 2], "dir": 0, "goal": [0, 2]}, {"done": true, "pos": [-1, -1], "dir": 0, "goal": [0, 2]}], "road": [[0.0, 0.0, 1.0, 1.0, 1.0, 0.0, 0.0, 0.0], [0.0, 0.0, 1.0, 1.0, 1.0, 0.0, 0.0, 0.0], [0.0, 0.0, 1.0, 1.0, 1.0, 0.0, 0.0, 0.0], [0.0, 0.0, 1.0, 1.0, 1.0, 0.0, 0.0, 0.0], [0.0, 0.0, 1.0, 1.0, 1.0, 0.0, 0.0, 0.0], [0.0, 0.0, 1.0, 1.0, 1.0, 0.0, 0.0, 0.0], [0.0, 0.0, 1.0, 1.0, 1.0, 0.0, 0.0, 0.0], [0.0, 0.0, 1.0, 1.0, 1.0, 0.0, 0.0, 0.0]]}, [{"action": 1, "message": "heading north now"}, {"action": 0, "message": ""}], {"cars": [{"done": false, "pos": [4, 2], "dir": 0, "goal": [0, 2]}, {"done": true, "pos": [-1, -1], "dir": 0, "goal": [0, 2]}], "road": [[0.0, 0.0, 1.0, 1.0, 1.0, 0.0, 0.0, 0.0], [0.0, 0.0, 1.0, 1.0, 1.0, 0.0, 0.0, 0.0], [0.0, 0.0, 1.0, 1.0, 1.0, 0.0, 0.0, 0.0], [0.0, 0.0, 1.0, 1.0, 1.0, 0.0, 0.0, 0.0], [0.0, 0.0, 1.0, 1.0, 1.0, 0.0, 0.0, 0.0], [0.0, 0.0, 1.0, 1.0, 1.0, 0.0, 0.0, 0.0], [0.0, 0.0, 1.0, 1.0, 1.0, 0.0, 0.0, 0.0], [0.0, 0.0, 1.0, 1.0, 1.0, 0.0, 0.0, 0.0]]}, [{"action": 1, "message": "good work!"}, {"action": 0, "message": ""}], {"cars": [{"done": false, "pos": [3, 2], "dir": 0, "goal": [0, 2]}, {"done": true, "pos": [-1, -1], "dir": 0, "goal": [0, 2]}], "road": [[0.0, 0.0, 1.0, 1.0, 1.0, 0.0, 0.0, 0.0], [0.0, 0.0, 1.0, 1.0, 1.0, 0.0, 0.0, 0.0], [0.0, 0.0, 1.0, 1.0, 1.0, 0.0, 0.0, 0.0], [0.0, 0.0, 1.0, 1.0, 1.0, 0.0, 0.0, 0.0], [0.0, 0.0, 1.0, 1.0, 1.0, 0.0, 0.0, 0.0], [0.0, 0.0, 1.0, 1.0, 1.0, 0.0, 0.0, 0.0], [0.0, 0.0, 1.0, 1.0, 1.0, 0.0, 0.0, 0.0], [0.0, 0.0, 1.0, 1.0, 1.0, 0.0, 0.0, 0.0]]}, [{"action": 1, "message": ""}, {"action": 0, "message": ""}], {"cars": [{"done": false, "pos": [2, 2], "dir": 0, "goal": [0, 2]}, {"done": true, "pos": [-1, -1], "dir": 0, "goal": [0, 2]}], "road": [[0.0, 0.0, 1.0, 1.0, 1.0, 0.0, 0.0, 0.0], [0.0, 0.0, 1.0, 1.0, 1.0, 0.0, 0.0, 0.0], [0.0, 0.0, 1.0, 1.0, 1.0, 0.0, 0.0, 0.0], [0.0, 0.0, 1.0, 1.0, 1.0, 0.0, 0.0, 0.0], [0.0, 0.0, 1.0, 1.0, 1.0, 0.0, 0.0, 0.0], [0.0, 0.0, 1.0, 1.0, 1.0, 0.0, 0.0, 0.0], [0.0, 0.0, 1.0, 1.0, 1.0, 0.0, 0.0, 0.0], [0.0, 0.0, 1.0, 1.0, 1.0, 0.0, 0.0, 0.0]]}, [{"action": 1, "message": ""}, {"action": 0, "message": ""}], {"cars": [{"done": false, "pos": [1, 2], "dir": 0, "goal": [0, 2]}, {"done": true, "pos": [-1, -1], "dir": 0, "goal": [0, 2]}], "road": [[0.0, 0.0, 1.0, 1.0, 1.0, 0.0, 0.0, 0.0], [0.0, 0.0, 1.0, 1.0, 1.0, 0.0, 0.0, 0.0], [0.0, 0.0, 1.0, 1.0, 1.0, 0.0, 0.0, 0.0], [0.0, 0.0, 1.0, 1.0, 1.0, 0.0, 0.0, 0.0], [0.0, 0.0, 1.0, 1.0, 1.0, 0.0, 0.0, 0.0], [0.0, 0.0, 1.0, 1.0, 1.0, 0.0, 0.0, 0.0], [0.0, 0.0, 1.0, 1.0, 1.0, 0.0, 0.0, 0.0], [0.0, 0.0, 1.0, 1.0, 1.0, 0.0, 0.0, 0.0]]}, [{"action": 1, "message": ""}, {"action": 0, "message": ""}], {"cars": [{"done": true, "pos": [0, 2], "dir": 0, "goal": [0, 2]}, {"done": true, "pos": [-1, -1], "dir": 0, "goal": [0, 2]}], "road": [[0.0, 0.0, 1.0, 1.0, 1.0, 0.0, 0.0, 0.0], [0.0, 0.0, 1.0, 1.0, 1.0, 0.0, 0.0, 0.0], [0.0, 0.0, 1.0, 1.0, 1.0, 0.0, 0.0, 0.0], [0.0, 0.0, 1.0, 1.0, 1.0, 0.0, 0.0, 0.0], [0.0, 0.0, 1.0, 1.0, 1.0, 0.0, 0.0, 0.0], [0.0, 0.0, 1.0, 1.0, 1.0, 0.0, 0.0, 0.0], [0.0, 0.0, 1.0, 1.0, 1.0, 0.0, 0.0, 0.0], [0.0, 0.0, 1.0, 1.0, 1.0, 0.0, 0.0, 0.0]]}]